kan/KANLayer.py
kan/LBFGS.py
kan/MLP.py
kan/MultKAN.py
kan/Symbolic_KANLayer.py
kan/__init__.py
kan/compiler.py
kan/experiment.py
kan/feynman.py
kan/hypothesis.py
kan/spline.py
kan/utils.py
kan/assets/img/mult_symbol.png
kan/assets/img/sum_symbol.png
pykan-0.2.8.dist-info/LICENSE
pykan-0.2.8.dist-info/METADATA
pykan-0.2.8.dist-info/WHEEL
pykan-0.2.8.dist-info/top_level.txt
pykan-0.2.8.dist-info/RECORD
